hermes_canopen_nodes/__init__.py
hermes_canopen_nodes/tools.py
hermes_canopen_nodes/device/__init__.py
hermes_canopen_nodes/device/canopen_entries.py
hermes_canopen_nodes/device/connection_manager.py
hermes_canopen_nodes/device/device.py
hermes_canopen_nodes/device/generic.py
hermes_canopen_nodes/device/mock_device.py
hermes_canopen_nodes/device/node.py
hermes_canopen_nodes/dll/usb2can.dll
hermes_canopen_nodes/network/__init__.py
hermes_canopen_nodes/network/generic_node.py
hermes_canopen_nodes/network/kvaeser_node.py
hermes_canopen_nodes/network/linux_node.py
hermes_canopen_nodes/network/universal_interface.py
hermes_canopen_nodes/network/universal_node.py
hermes_canopen_nodes/network/usb2can_node.py
hermes_canopen_nodes/network/ui/interface.py
hermes_canopen_nodes/network/ui/interface.ui
hermes_canopen_nodes-1.0.0.dist-info/METADATA
hermes_canopen_nodes-1.0.0.dist-info/WHEEL
hermes_canopen_nodes-1.0.0.dist-info/RECORD
