Metadata-Version: 2.4
Name: hermes-canopen-nodes
Version: 1.0.0
Summary: Nodes to interact with canopen 
Author-email: floris vernieuwe <floris@vernieuwe.eu>
Requires-Python: >=3.10
Requires-Dist: asyncslot>=0.3.1
Requires-Dist: canopen>=2.3.0
Requires-Dist: node-hermes-core>=1.2.0
Requires-Dist: node-hermes-qt>=1.2.1
Requires-Dist: pydantic>=2.10.6
